[
    {
        "createdAt": "2023-06-28 17:17:43.815 +00:00",
        "current": "socialmedia",
        "facebook": null,
        "instagram": null,
        "name": "Maffin",
        "reddit": "1563015740",
        "resigned": null,
        "socialmedia": "1563015740",
        "twitter": null,
        "updatedAt": "2023-06-28 17:17:43.815 +00:00"
    },
    {
        "createdAt": "2023-06-28 17:17:43.815 +00:00",
        "current": "socialmedia",
        "facebook": "1578826940",
        "instagram": null,
        "name": "Lisa",
        "reddit": null,
        "resigned": null,
        "socialmedia": "1578826940",
        "twitter": null,
        "updatedAt": "2023-06-28 17:17:43.815 +00:00"
    },
    {
        "createdAt": "2023-06-28 17:17:43.815 +00:00",
        "current": "socialmedia",
        "facebook": "1578826940",
        "instagram": null,
        "name": "Arnaud",
        "reddit": null,
        "resigned": null,
        "socialmedia": "1578826940 1605105445",
        "twitter": "1605105445",
        "updatedAt": "2023-06-28 17:17:43.815 +00:00"
    },
    {
        "createdAt": "2023-06-28 17:17:43.815 +00:00",
        "current": "resigned",
        "facebook": "1578826940",
        "instagram": null,
        "name": "Hyde",
        "reddit": null,
        "resigned": 1650126784,
        "socialmedia": "1578826940",
        "twitter": null,
        "updatedAt": "2023-06-28 17:17:43.815 +00:00"
    },
    {
        "createdAt": "2023-06-28 17:17:43.815 +00:00",
        "current": "resigned",
        "facebook": "1552993340",
        "instagram": null,
        "name": "Camp",
        "reddit": null,
        "resigned": 1578826940,
        "socialmedia": "1552993340",
        "twitter": null,
        "updatedAt": "2023-06-28 17:17:43.815 +00:00"
    },
    {
        "createdAt": "2023-06-28 17:17:43.815 +00:00",
        "current": "socialmedia",
        "facebook": null,
        "instagram": "1552820540",
        "name": "Sharon",
        "reddit": null,
        "resigned": null,
        "socialmedia": "1552820540",
        "twitter": null,
        "updatedAt": "2023-06-28 17:17:43.815 +00:00"
    },
    {
        "createdAt": "2023-06-28 17:17:43.815 +00:00",
        "current": "resigned",
        "facebook": null,
        "instagram": "1561460540",
        "name": "Crush",
        "reddit": null,
        "resigned": 1573556540,
        "socialmedia": "1561460540",
        "twitter": null,
        "updatedAt": "2023-06-28 17:17:43.815 +00:00"
    },
    {
        "createdAt": "2023-06-28 17:17:43.815 +00:00",
        "current": "socialmedia",
        "facebook": null,
        "instagram": "1573556540",
        "name": "Duden",
        "reddit": null,
        "resigned": null,
        "socialmedia": "1573556540 1605105445",
        "twitter": "1605105445",
        "updatedAt": "2023-06-28 17:17:43.815 +00:00"
    },
    {
        "createdAt": "2023-06-28 17:17:43.815 +00:00",
        "current": "resigned",
        "facebook": null,
        "instagram": "1567508540",
        "name": "Stef",
        "reddit": null,
        "resigned": 1623497301,
        "socialmedia": "1567508540",
        "twitter": null,
        "updatedAt": "2023-06-28 17:17:43.815 +00:00"
    },
    {
        "createdAt": "2023-06-28 17:17:43.815 +00:00",
        "current": "socialmedia",
        "facebook": null,
        "instagram": "1595502140 1622028501",
        "name": "Bunno",
        "reddit": null,
        "resigned": 1611311243,
        "socialmedia": "1595502140 1622028501",
        "twitter": null,
        "updatedAt": "2023-06-28 17:17:43.815 +00:00"
    },
    {
        "createdAt": "2023-06-28 17:17:43.815 +00:00",
        "current": "resigned",
        "facebook": "1539594154",
        "instagram": null,
        "name": "Maya",
        "reddit": null,
        "resigned": 1553019021,
        "socialmedia": "1539594154",
        "twitter": null,
        "updatedAt": "2023-06-28 17:17:43.815 +00:00"
    },
    {
        "createdAt": "2023-06-28 17:17:43.816 +00:00",
        "current": "resigned",
        "facebook": null,
        "instagram": null,
        "name": "Lucienbl",
        "reddit": null,
        "resigned": 1569920554,
        "socialmedia": "1539594154",
        "twitter": "1539594154",
        "updatedAt": "2023-06-28 17:17:43.816 +00:00"
    },
    {
        "createdAt": "2023-06-28 17:17:43.816 +00:00",
        "current": "resigned",
        "facebook": null,
        "instagram": null,
        "name": "Milky",
        "reddit": null,
        "resigned": 1554282154,
        "socialmedia": "1540890154",
        "twitter": "1540890154",
        "updatedAt": "2023-06-28 17:17:43.816 +00:00"
    },
    {
        "createdAt": "2023-06-28 17:17:43.816 +00:00",
        "current": "resigned",
        "facebook": "1554627754",
        "instagram": null,
        "name": "Prometheus",
        "reddit": null,
        "resigned": 1557738154,
        "socialmedia": "1554627754",
        "twitter": null,
        "updatedAt": "2023-06-28 17:17:43.816 +00:00"
    },
    {
        "createdAt": "2023-06-28 17:17:43.816 +00:00",
        "current": "resigned",
        "facebook": null,
        "instagram": "1611341921",
        "name": "Pan",
        "reddit": null,
        "resigned": 1632337615,
        "socialmedia": "1611341921",
        "twitter": null,
        "updatedAt": "2023-06-28 17:17:43.816 +00:00"
    },
    {
        "createdAt": "2023-06-28 17:17:43.816 +00:00",
        "current": "socialmedia",
        "facebook": "1558004540",
        "instagram": null,
        "name": "Chris Phil",
        "reddit": null,
        "resigned": null,
        "socialmedia": "1558004540 1558004541",
        "twitter": "1558004541",
        "updatedAt": "2023-06-28 17:17:43.816 +00:00"
    },
    {
        "createdAt": "2023-06-28 17:17:43.816 +00:00",
        "current": "socialmedia",
        "facebook": null,
        "instagram": "1624302539",
        "name": "Leon",
        "reddit": null,
        "resigned": null,
        "socialmedia": "1624302539",
        "twitter": null,
        "updatedAt": "2023-06-28 17:17:43.816 +00:00"
    }
]